huaweicloudsdkkvs/__init__.py
huaweicloudsdkkvs/v1/__init__.py
huaweicloudsdkkvs/v1/abstract_multichannel_kvs_client.py
huaweicloudsdkkvs/v1/kvs_async_client.py
huaweicloudsdkkvs/v1/kvs_async_client_interface.py
huaweicloudsdkkvs/v1/kvs_client.py
huaweicloudsdkkvs/v1/kvs_client_heartbeat_keeper.py
huaweicloudsdkkvs/v1/kvs_client_interface.py
huaweicloudsdkkvs/v1/kvs_exception_handler.py
huaweicloudsdkkvs/v1/managed_kvs_client.py
huaweicloudsdkkvs/v1/multichannel_kvs_async_client.py
huaweicloudsdkkvs/v1/multichannel_kvs_client.py
huaweicloudsdkkvs/v1/config/__init__.py
huaweicloudsdkkvs/v1/config/kvs_sdk_config.py
huaweicloudsdkkvs/v1/config/kvs_sdk_config_manager.py
huaweicloudsdkkvs/v1/model/__init__.py
huaweicloudsdkkvs/v1/model/batch_get_kv_of_table.py
huaweicloudsdkkvs/v1/model/batch_get_kv_request.py
huaweicloudsdkkvs/v1/model/batch_get_kv_request_body.py
huaweicloudsdkkvs/v1/model/batch_get_kv_response.py
huaweicloudsdkkvs/v1/model/batch_write_kv_request.py
huaweicloudsdkkvs/v1/model/batch_write_kv_request_body.py
huaweicloudsdkkvs/v1/model/batch_write_kv_response.py
huaweicloudsdkkvs/v1/model/check_health_request.py
huaweicloudsdkkvs/v1/model/check_health_request_body.py
huaweicloudsdkkvs/v1/model/check_health_response.py
huaweicloudsdkkvs/v1/model/composed_expression.py
huaweicloudsdkkvs/v1/model/condition_expression.py
huaweicloudsdkkvs/v1/model/create_table_request.py
huaweicloudsdkkvs/v1/model/create_table_request_body.py
huaweicloudsdkkvs/v1/model/create_table_response.py
huaweicloudsdkkvs/v1/model/credential.py
huaweicloudsdkkvs/v1/model/delete_kv.py
huaweicloudsdkkvs/v1/model/delete_kv_request.py
huaweicloudsdkkvs/v1/model/delete_kv_request_body.py
huaweicloudsdkkvs/v1/model/delete_kv_response.py
huaweicloudsdkkvs/v1/model/delete_table_request.py
huaweicloudsdkkvs/v1/model/delete_table_request_body.py
huaweicloudsdkkvs/v1/model/delete_table_response.py
huaweicloudsdkkvs/v1/model/describe_table_request.py
huaweicloudsdkkvs-3.1.184.dist-info/METADATA
huaweicloudsdkkvs-3.1.184.dist-info/WHEEL
huaweicloudsdkkvs-3.1.184.dist-info/licenses/LICENSE
huaweicloudsdkkvs-3.1.184.dist-info/RECORD
